library.theme-1.1.7-py3.8-nspkg.pth
library/theme/__init__.py
library/theme/configure.zcml
library/theme/interfaces.py
library/theme/setuphandlers.py
library/theme/testing.py
library/theme/browser/__init__.py
library/theme/browser/configure.zcml
library/theme/browser/overrides/.gitkeep
library/theme/browser/static/.gitkeep
library/theme/locales/library.theme.pot
library/theme/locales/update.sh
library/theme/profiles/default/browserlayer.xml
library/theme/profiles/default/metadata.xml
library/theme/profiles/default/registry.xml
library/theme/profiles/default/theme.xml
library/theme/profiles/default/viewlets.xml
library/theme/profiles/uninstall/browserlayer.xml
library/theme/profiles/uninstall/theme.xml
library/theme/tests/__init__.py
library/theme/tests/test_robot.py
library/theme/tests/test_setup.py
library/theme/tests/robot/test_example.robot
library/theme/theme/backend.xml
library/theme/theme/index.html
library/theme/theme/manifest.cfg
library/theme/theme/rules.xml
library/theme/theme/barceloneta/BARCELONETA-UPDATE.rst
library/theme/theme/barceloneta/BARCELONETA-VERSION.rst
library/theme/theme/barceloneta/backend.xml
library/theme/theme/barceloneta/barceloneta-apple-touch-icon-114x114-precomposed.png
library/theme/theme/barceloneta/barceloneta-apple-touch-icon-144x144-precomposed.png
library/theme/theme/barceloneta/barceloneta-apple-touch-icon-57x57-precomposed.png
library/theme/theme/barceloneta/barceloneta-apple-touch-icon-72x72-precomposed.png
library/theme/theme/barceloneta/barceloneta-apple-touch-icon-precomposed.png
library/theme/theme/barceloneta/barceloneta-apple-touch-icon.png
library/theme/theme/barceloneta/barceloneta-favicon.ico
library/theme/theme/barceloneta/less/accessibility.plone.less
library/theme/theme/barceloneta/less/alerts.plone.less
library/theme/theme/barceloneta/less/barceloneta-compiled.css
library/theme/theme/barceloneta/less/barceloneta-compiled.css.map
library/theme/theme/barceloneta/less/barceloneta.css.original-reference
library.theme-1.1.7.dist-info/LICENSE.GPL
library.theme-1.1.7.dist-info/LICENSE.rst
library.theme-1.1.7.dist-info/METADATA
library.theme-1.1.7.dist-info/WHEEL
library.theme-1.1.7.dist-info/entry_points.txt
library.theme-1.1.7.dist-info/namespace_packages.txt
library.theme-1.1.7.dist-info/top_level.txt
library.theme-1.1.7.dist-info/RECORD
